---

title: "NPE in TCDistributedCacheExpirationTest"
layout: issue
tags: 
permalink: /browse/CDV-1209

issue_key: CDV-1209
issue_numeric_sort_key: 1209
issuetype: "Bug"
project: "Community Development (Terracotta Server)"
project_key: "CDV"
status: "Closed"
resolution: "Won't Fix"
priority: "2 Major"
components: ""
labels: 
assignee: "teck"
reporter: "teck"
votes:  0
watchers: 1

created: "2009-03-18T19:03:08.000-0400"
updated: "2012-07-27T19:59:38.000-0400"
resolved: "2009-05-29T16:48:48.000-0400"

---



{% raw %}


## Attachments
  
* <em>teck</em> (51.000 k, application/gzip) [log-tim-tccache-trunk-s10fm0-20090314062234.txt.gz](/attachments/CDV/CDV-1209/log-tim-tccache-trunk-s10fm0-20090314062234.txt.gz)
  



## Description

<div markdown="1" class="description">

I'm creating this JIRA to keep a record of it. It is a complete mystery how this can get generated (there is no apparent StringBuilder in there). I don't think it needs a target unless we see it again

java.lang.NullPointerException
at java.lang.StringBuilder.append(StringBuilder.java:55)
at org.terracotta.modules.dmap.impl.Timestamp.\1\1tc\1wrapped\1expiresAt(Timestamp.java:117)
at org.terracotta.modules.dmap.impl.Timestamp.expiresAt(Timestamp.java)
at org.terracotta.modules.dmap.impl.Timestamp.isExpired(Timestamp.java:106)
at org.terracotta.modules.tccache.StoreImpl.checkExpired(StoreImpl.java:185)
at org.terracotta.modules.tccache.StoreImpl.get(StoreImpl.java:122)
at org.terracotta.modules.tccache.TCDistributedCacheImpl.get(TCDistributedCacheImpl.java:95)
at org.terracotta.modules.tccache.TCDistributedCacheExpirationTest$App$1.run(TCDistributedCacheExpirationTest.java:132)


</div>

## Comments


{:.comment-heading}
### **Geert Bevin** <span class="date">2009-03-25</span>

<div markdown="1" class="comment">

I took a look at this and it's indeed mysterious.

When I look at the adapted bytecode I see that line number 117 is actually the first line of the adapted method. This makes me wonder if there's maybe another tool installed that might be instrumenting bytecode, like a profiler or some aspect thingie.

private long \1\1tc\1wrapped\1expiresAt();
  Code:
   Stack=4, Locals=3, Args\1size=1
   0:	aload\10
   1:	invokevirtual	#155; //Method \1\1tc\1getexpiresFromTTLAt:()J
   4:	lstore\11
   5:	aload\10
   6:	invokevirtual	#155; //Method \1\1tc\1getexpiresFromTTLAt:()J
   9:	lconst\10
   10:	lcmp
   11:	ifeq	32
   14:	aload\10
   15:	invokevirtual	#142; //Method \1\1tc\1getexpiresFromTTIAt:()J
   18:	lconst\10
   19:	lcmp
   20:	ifeq	37
   23:	aload\10
   24:	invokevirtual	#142; //Method \1\1tc\1getexpiresFromTTIAt:()J
   27:	lload\11
   28:	lcmp
   29:	ifge	37
   32:	aload\10
   33:	invokevirtual	#142; //Method \1\1tc\1getexpiresFromTTIAt:()J
   36:	lstore\11
   37:	lload\11
   38:	lreturn
  LocalVariableTable: 
   Start  Length  Slot  Name   Signature
   0      39      0    this       Lorg/terracotta/modules/dmap/impl/Timestamp;
   5      34      1    expiresAt       J
  LineNumberTable: 
   line 117: 0
   line 119: 5
   line 120: 32
   line 123: 37


</div>


{:.comment-heading}
### **Tim Eck** <span class="date">2009-05-29</span>

<div markdown="1" class="comment">

Haven't seen this again and I'm going to chalk this one up to the general flakiness of solaris 1.6 client VM (like MNK-1005)

</div>



{% endraw %}
